groot_ansible/__init__.py
groot_ansible/common.py
groot_ansible/console.py
groot_ansible/ros.py
groot_ansible/testies.py
groot_ansible/update.py
groot_ansible/workstation.py
groot_ansible/playbooks/bootstrap-daniel.yaml
groot_ansible/playbooks/bootstrap-pc.yaml
groot_ansible/playbooks/devel-git.yaml
groot_ansible/playbooks/devel-powerline.yaml
groot_ansible/playbooks/devel-ros1.yaml
groot_ansible/playbooks/devel-ros2.yaml
groot_ansible/playbooks/extras-chrome.yaml
groot_ansible/playbooks/extras-snorriheim.yaml
groot_ansible/playbooks/extras-vscode.yaml
groot_ansible/playbooks/os-kubuntu.yaml
groot_ansible/playbooks/os-system76.yaml
groot_ansible/playbooks/os-ubuntu.yaml
groot_ansible/playbooks/utils-testies.yaml
groot_ansible/playbooks/utils-update.yaml
groot_ansible/playbooks/library/Readme.md
groot_ansible/playbooks/library/vci.py
groot_ansible/playbooks/library/vci_config.py
groot_ansible/playbooks/roles/chrome/defaults/main.yaml
groot_ansible/playbooks/roles/chrome/meta/main.yaml
groot_ansible/playbooks/roles/chrome/tasks/main.yaml
groot_ansible/playbooks/roles/git/defaults/main.yaml
groot_ansible/playbooks/roles/git/meta/main.yaml
groot_ansible/playbooks/roles/git/tasks/main.yaml
groot_ansible/playbooks/roles/git/templates/gitconfig.j2
groot_ansible/playbooks/roles/groot/workstation/defaults/main.yaml
groot_ansible/playbooks/roles/groot/workstation/meta/main.yaml
groot_ansible/playbooks/roles/groot/workstation/tasks/gpg.yaml
groot_ansible/playbooks/roles/groot/workstation/tasks/konsole.yaml
groot_ansible/playbooks/roles/groot/workstation/tasks/language.yaml
groot_ansible/playbooks/roles/groot/workstation/tasks/main.yaml
groot_ansible/playbooks/roles/groot/workstation/tasks/python.yaml
groot_ansible/playbooks/roles/groot/workstation/tasks/sysadmin.yaml
groot_ansible/playbooks/roles/groot/workstation/tasks/workspaces.yaml
groot_ansible/playbooks/roles/groot/workstation/tasks/xelatex.yaml
groot_ansible/playbooks/roles/groot/workstation/templates/bash_aliases.j2
groot_ansible-0.4.3.dist-info/LICENSE
groot_ansible-0.4.3.dist-info/METADATA
groot_ansible-0.4.3.dist-info/WHEEL
groot_ansible-0.4.3.dist-info/entry_points.txt
groot_ansible-0.4.3.dist-info/top_level.txt
groot_ansible-0.4.3.dist-info/RECORD
