Metadata-Version: 2.1
Name: groot-ansible
Version: 0.4.3
Summary: system installation and update scripts
Home-page: http://github.com/stonier/groot_ansible
Author: Daniel Stonier
Author-email: d.stonier@gmail.com
Maintainer: Daniel Stonier
Maintainer-email: d.stonier@gmail.com
License: BSD
Keywords: catkin
Platform: UNKNOWN
Classifier: Environment :: Console
Classifier: Intended Audience :: Developers
Classifier: License :: OSI Approved :: BSD License
Classifier: Programming Language :: Python
Classifier: Topic :: System :: Systems Administration
Classifier: Topic :: Utilities
